django_pgviews/__init__.py
django_pgviews/apps.py
django_pgviews/models.py
django_pgviews/signals.py
django_pgviews/view.py
django_pgviews/db/__init__.py
django_pgviews/db/sql/__init__.py
django_pgviews/db/sql/compiler.py
django_pgviews/db/sql/query.py
django_pgviews/management/__init__.py
django_pgviews/management/commands/__init__.py
django_pgviews/management/commands/clear_pgviews.py
django_pgviews/management/commands/sync_pgviews.py
django_pgviews-0.6.0.dist-info/METADATA
django_pgviews-0.6.0.dist-info/WHEEL
django_pgviews-0.6.0.dist-info/top_level.txt
django_pgviews-0.6.0.dist-info/RECORD
