Metadata-Version: 2.1
Name: django-pgviews
Version: 0.6.0
Summary: Create and manage Postgres SQL Views in Django
Home-page: https://github.com/mypebble/django-pgviews
Author: Scott Walton
Author-email: scott.walton@mypebble.co.uk
License: Public Domain
Classifier: Development Status :: 5 - Production/Stable
Classifier: Programming Language :: Python
Classifier: Programming Language :: Python :: 3.8
Classifier: Programming Language :: Python :: 3.9
Classifier: Programming Language :: Python :: 3.10
Classifier: Programming Language :: Python :: 3.11
Classifier: Programming Language :: Python :: 3.12
Classifier: Framework :: Django
Classifier: Framework :: Django :: 4.0
Classifier: Framework :: Django :: 4.1
Classifier: Framework :: Django :: 4.2
Requires-Dist: six
